{
  "updated": "2025-11-07 15:41 ET",
  "stocks": {
    "AAPL": {
      "symbol": "AAPL",
      "price": 268.07,
      "prevClose": 268.07,
      "updated": "2025-11-07 15:41 ET"
    },
    "MSFT": {
      "symbol": "MSFT",
      "price": 496.33,
      "prevClose": 496.33,
      "updated": "2025-11-07 15:41 ET"
    },
    "GOOGL": {
      "symbol": "GOOGL",
      "price": 278.55,
      "prevClose": 278.55,
      "updated": "2025-11-07 15:41 ET"
    },
    "AMZN": {
      "symbol": "AMZN",
      "price": 244.44,
      "prevClose": 244.44,
      "updated": "2025-11-07 15:41 ET"
    },
    "TSLA": {
      "symbol": "TSLA",
      "price": 431.45,
      "prevClose": 431.45,
      "updated": "2025-11-07 15:41 ET"
    },
    "META": {
      "symbol": "META",
      "price": 618.63,
      "prevClose": 618.63,
      "updated": "2025-11-07 15:41 ET"
    },
    "NVDA": {
      "symbol": "NVDA",
      "price": 187.01,
      "prevClose": 187.01,
      "updated": "2025-11-07 15:41 ET"
    },
    "AMD": {
      "symbol": "AMD",
      "price": 230.74,
      "prevClose": 230.74,
      "updated": "2025-11-07 15:41 ET"
    },
    "NFLX": {
      "symbol": "NFLX",
      "price": 1099.65,
      "prevClose": 1099.65,
      "updated": "2025-11-07 15:41 ET"
    },
    "DIS": {
      "symbol": "DIS",
      "price": 110.63,
      "prevClose": 110.63,
      "updated": "2025-11-07 15:41 ET"
    },
    "PYPL": {
      "symbol": "PYPL",
      "price": 66.21,
      "prevClose": 66.21,
      "updated": "2025-11-07 15:41 ET"
    },
    "XYZ": {
      "symbol": "XYZ",
      "price": 65.48,
      "prevClose": 65.48,
      "updated": "2025-11-07 15:41 ET"
    },
    "COIN": {
      "symbol": "COIN",
      "price": 309.41,
      "prevClose": 309.41,
      "updated": "2025-11-07 15:41 ET"
    },
    "SHOP": {
      "symbol": "SHOP",
      "price": 152.15,
      "prevClose": 152.15,
      "updated": "2025-11-07 15:41 ET"
    },
    "UBER": {
      "symbol": "UBER",
      "price": 92.0,
      "prevClose": 92.0,
      "updated": "2025-11-07 15:41 ET"
    },
    "LYFT": {
      "symbol": "LYFT",
      "price": 21.67,
      "prevClose": 21.67,
      "updated": "2025-11-07 15:41 ET"
    },
    "SNAP": {
      "symbol": "SNAP",
      "price": 8.22,
      "prevClose": 8.22,
      "updated": "2025-11-07 15:41 ET"
    },
    "SPOT": {
      "symbol": "SPOT",
      "price": 614.95,
      "prevClose": 614.95,
      "updated": "2025-11-07 15:41 ET"
    },
    "RBLX": {
      "symbol": "RBLX",
      "price": 106.99,
      "prevClose": 106.99,
      "updated": "2025-11-07 15:41 ET"
    },
    "ROKU": {
      "symbol": "ROKU",
      "price": 101.51,
      "prevClose": 101.51,
      "updated": "2025-11-07 15:41 ET"
    },
    "HOOD": {
      "symbol": "HOOD",
      "price": 128.3,
      "prevClose": 128.3,
      "updated": "2025-11-07 15:41 ET"
    },
    "SOFI": {
      "symbol": "SOFI",
      "price": 27.83,
      "prevClose": 27.83,
      "updated": "2025-11-07 15:41 ET"
    },
    "PLTR": {
      "symbol": "PLTR",
      "price": 177.35,
      "prevClose": 177.35,
      "updated": "2025-11-07 15:41 ET"
    },
    "ABNB": {
      "symbol": "ABNB",
      "price": 120.95,
      "prevClose": 120.95,
      "updated": "2025-11-07 15:41 ET"
    },
    "DASH": {
      "symbol": "DASH",
      "price": 205.63,
      "prevClose": 205.63,
      "updated": "2025-11-07 15:41 ET"
    },
    "SNOW": {
      "symbol": "SNOW",
      "price": 262.0,
      "prevClose": 262.0,
      "updated": "2025-11-07 15:41 ET"
    },
    "NET": {
      "symbol": "NET",
      "price": 230.92,
      "prevClose": 230.92,
      "updated": "2025-11-07 15:41 ET"
    },
    "DKNG": {
      "symbol": "DKNG",
      "price": 29.83,
      "prevClose": 29.83,
      "updated": "2025-11-07 15:41 ET"
    },
    "PINS": {
      "symbol": "PINS",
      "price": 27.07,
      "prevClose": 27.07,
      "updated": "2025-11-07 15:41 ET"
    },
    "TWLO": {
      "symbol": "TWLO",
      "price": 127.43,
      "prevClose": 127.43,
      "updated": "2025-11-07 15:41 ET"
    },
    "ZM": {
      "symbol": "ZM",
      "price": 81.57,
      "prevClose": 81.57,
      "updated": "2025-11-07 15:41 ET"
    },
    "DOCU": {
      "symbol": "DOCU",
      "price": 69.64,
      "prevClose": 69.64,
      "updated": "2025-11-07 15:41 ET"
    },
    "CRM": {
      "symbol": "CRM",
      "price": 239.37,
      "prevClose": 239.37,
      "updated": "2025-11-07 15:41 ET"
    },
    "ORCL": {
      "symbol": "ORCL",
      "price": 244.13,
      "prevClose": 244.13,
      "updated": "2025-11-06 15:44 ET"
    },
    "INTC": {
      "symbol": "INTC",
      "price": 37.72,
      "prevClose": 37.72,
      "updated": "2025-11-07 15:41 ET"
    },
    "IBM": {
      "symbol": "IBM",
      "price": 306.5,
      "prevClose": 306.5,
      "updated": "2025-11-07 15:41 ET"
    },
    "CSCO": {
      "symbol": "CSCO",
      "price": 70.92,
      "prevClose": 70.92,
      "updated": "2025-11-07 15:41 ET"
    },
    "ADBE": {
      "symbol": "ADBE",
      "price": 325.11,
      "prevClose": 325.11,
      "updated": "2025-11-07 15:41 ET"
    },
    "NOW": {
      "symbol": "NOW",
      "price": 859.82,
      "prevClose": 859.82,
      "updated": "2025-11-06 15:44 ET"
    },
    "INTU": {
      "symbol": "INTU",
      "price": 648.14,
      "prevClose": 648.14,
      "updated": "2025-11-07 15:41 ET"
    },
    "TXN": {
      "symbol": "TXN",
      "price": 159.4,
      "prevClose": 159.4,
      "updated": "2025-11-07 15:41 ET"
    },
    "QCOM": {
      "symbol": "QCOM",
      "price": 169.61,
      "prevClose": 169.61,
      "updated": "2025-11-07 15:41 ET"
    },
    "AVGO": {
      "symbol": "AVGO",
      "price": 346.58,
      "prevClose": 346.58,
      "updated": "2025-11-07 15:41 ET"
    },
    "MU": {
      "symbol": "MU",
      "price": 235.51,
      "prevClose": 235.51,
      "updated": "2025-11-07 15:41 ET"
    },
    "AMAT": {
      "symbol": "AMAT",
      "price": 228.15,
      "prevClose": 228.15,
      "updated": "2025-11-07 15:41 ET"
    },
    "LRCX": {
      "symbol": "LRCX",
      "price": 158.09,
      "prevClose": 158.09,
      "updated": "2025-11-07 15:41 ET"
    },
    "KLAC": {
      "symbol": "KLAC",
      "price": 1186.42,
      "prevClose": 1186.42,
      "updated": "2025-11-07 15:41 ET"
    },
    "MRVL": {
      "symbol": "MRVL",
      "price": 89.77,
      "prevClose": 89.77,
      "updated": "2025-11-07 15:41 ET"
    },
    "ON": {
      "symbol": "ON",
      "price": 47.42,
      "prevClose": 47.42,
      "updated": "2025-11-07 15:41 ET"
    },
    "ARM": {
      "symbol": "ARM",
      "price": 151.21,
      "prevClose": 151.21,
      "updated": "2025-11-07 15:41 ET"
    },
    "SMCI": {
      "symbol": "SMCI",
      "price": 39.57,
      "prevClose": 39.57,
      "updated": "2025-11-07 15:41 ET"
    },
    "DELL": {
      "symbol": "DELL",
      "price": 145.5,
      "prevClose": 145.5,
      "updated": "2025-11-07 15:41 ET"
    },
    "HPE": {
      "symbol": "HPE",
      "price": 23.33,
      "prevClose": 23.33,
      "updated": "2025-11-07 15:41 ET"
    },
    "WDC": {
      "symbol": "WDC",
      "price": 161.65,
      "prevClose": 161.65,
      "updated": "2025-11-07 15:41 ET"
    },
    "STX": {
      "symbol": "STX",
      "price": 278.15,
      "prevClose": 278.15,
      "updated": "2025-11-07 15:41 ET"
    },
    "PSTG": {
      "symbol": "PSTG",
      "price": 89.35,
      "prevClose": 89.35,
      "updated": "2025-11-07 15:41 ET"
    },
    "JPM": {
      "symbol": "JPM",
      "price": 313.44,
      "prevClose": 313.44,
      "updated": "2025-11-07 15:41 ET"
    },
    "BAC": {
      "symbol": "BAC",
      "price": 53.2,
      "prevClose": 53.2,
      "updated": "2025-11-07 15:41 ET"
    },
    "WFC": {
      "symbol": "WFC",
      "price": 85.82,
      "prevClose": 85.82,
      "updated": "2025-11-07 15:41 ET"
    },
    "GS": {
      "symbol": "GS",
      "price": 782.18,
      "prevClose": 782.18,
      "updated": "2025-11-07 15:41 ET"
    },
    "MS": {
      "symbol": "MS",
      "price": 162.19,
      "prevClose": 162.19,
      "updated": "2025-11-07 15:41 ET"
    },
    "C": {
      "symbol": "C",
      "price": 101.23,
      "prevClose": 101.23,
      "updated": "2025-11-06 15:44 ET"
    },
    "BLK": {
      "symbol": "BLK",
      "price": 1080.35,
      "prevClose": 1080.35,
      "updated": "2025-11-07 15:41 ET"
    },
    "SCHW": {
      "symbol": "SCHW",
      "price": 95.26,
      "prevClose": 95.26,
      "updated": "2025-11-07 15:41 ET"
    },
    "AXP": {
      "symbol": "AXP",
      "price": 367.69,
      "prevClose": 367.69,
      "updated": "2025-11-07 15:41 ET"
    },
    "V": {
      "symbol": "V",
      "price": 336.23,
      "prevClose": 336.23,
      "updated": "2025-11-07 15:41 ET"
    },
    "MA": {
      "symbol": "MA",
      "price": 551.2,
      "prevClose": 551.2,
      "updated": "2025-11-07 15:41 ET"
    },
    "COF": {
      "symbol": "COF",
      "price": 217.07,
      "prevClose": 217.07,
      "updated": "2025-11-07 15:41 ET"
    },
    "SYF": {
      "symbol": "SYF",
      "price": 73.2,
      "prevClose": 73.2,
      "updated": "2025-11-07 15:41 ET"
    },
    "ALLY": {
      "symbol": "ALLY",
      "price": 39.1,
      "prevClose": 39.1,
      "updated": "2025-11-07 15:41 ET"
    },
    "JNJ": {
      "symbol": "JNJ",
      "price": 186.44,
      "prevClose": 186.44,
      "updated": "2025-11-07 15:41 ET"
    },
    "UNH": {
      "symbol": "UNH",
      "price": 321.14,
      "prevClose": 321.14,
      "updated": "2025-11-07 15:41 ET"
    },
    "PFE": {
      "symbol": "PFE",
      "price": 24.34,
      "prevClose": 24.34,
      "updated": "2025-11-07 15:41 ET"
    },
    "ABBV": {
      "symbol": "ABBV",
      "price": 218.04,
      "prevClose": 218.04,
      "updated": "2025-11-07 15:41 ET"
    },
    "TMO": {
      "symbol": "TMO",
      "price": 572.04,
      "prevClose": 572.04,
      "updated": "2025-11-07 15:41 ET"
    },
    "ABT": {
      "symbol": "ABT",
      "price": 126.05,
      "prevClose": 126.05,
      "updated": "2025-11-07 15:41 ET"
    },
    "DHR": {
      "symbol": "DHR",
      "price": 209.34,
      "prevClose": 209.34,
      "updated": "2025-11-07 15:41 ET"
    },
    "LLY": {
      "symbol": "LLY",
      "price": 917.76,
      "prevClose": 917.76,
      "updated": "2025-11-07 15:41 ET"
    },
    "MRK": {
      "symbol": "MRK",
      "price": 85.96,
      "prevClose": 85.96,
      "updated": "2025-11-07 15:41 ET"
    },
    "BMY": {
      "symbol": "BMY",
      "price": 46.69,
      "prevClose": 46.69,
      "updated": "2025-11-07 15:41 ET"
    },
    "AMGN": {
      "symbol": "AMGN",
      "price": 319.36,
      "prevClose": 319.36,
      "updated": "2025-11-07 15:41 ET"
    },
    "GILD": {
      "symbol": "GILD",
      "price": 118.25,
      "prevClose": 118.25,
      "updated": "2025-11-07 15:41 ET"
    },
    "VRTX": {
      "symbol": "VRTX",
      "price": 407.99,
      "prevClose": 407.99,
      "updated": "2025-11-07 15:41 ET"
    },
    "BIIB": {
      "symbol": "BIIB",
      "price": 154.08,
      "prevClose": 154.08,
      "updated": "2025-11-07 15:41 ET"
    },
    "REGN": {
      "symbol": "REGN",
      "price": 655.1,
      "prevClose": 655.1,
      "updated": "2025-11-07 15:41 ET"
    },
    "MRNA": {
      "symbol": "MRNA",
      "price": 24.31,
      "prevClose": 24.31,
      "updated": "2025-11-07 15:41 ET"
    },
    "BNTX": {
      "symbol": "BNTX",
      "price": 102.39,
      "prevClose": 102.39,
      "updated": "2025-11-07 15:41 ET"
    },
    "NVAX": {
      "symbol": "NVAX",
      "price": 7.38,
      "prevClose": 7.38,
      "updated": "2025-11-07 15:41 ET"
    },
    "XOM": {
      "symbol": "XOM",
      "price": 117.32,
      "prevClose": 117.32,
      "updated": "2025-11-07 15:41 ET"
    },
    "CVX": {
      "symbol": "CVX",
      "price": 155.3,
      "prevClose": 155.3,
      "updated": "2025-11-07 15:41 ET"
    },
    "COP": {
      "symbol": "COP",
      "price": 86.9,
      "prevClose": 86.9,
      "updated": "2025-11-07 15:41 ET"
    },
    "SLB": {
      "symbol": "SLB",
      "price": 36.51,
      "prevClose": 36.51,
      "updated": "2025-11-07 15:41 ET"
    },
    "EOG": {
      "symbol": "EOG",
      "price": 105.5,
      "prevClose": 105.5,
      "updated": "2025-11-07 15:41 ET"
    },
    "MPC": {
      "symbol": "MPC",
      "price": 193.92,
      "prevClose": 193.92,
      "updated": "2025-11-07 15:41 ET"
    },
    "VLO": {
      "symbol": "VLO",
      "price": 175.55,
      "prevClose": 175.55,
      "updated": "2025-11-07 15:41 ET"
    },
    "PSX": {
      "symbol": "PSX",
      "price": 137.67,
      "prevClose": 137.67,
      "updated": "2025-11-07 15:41 ET"
    },
    "OXY": {
      "symbol": "OXY",
      "price": 41.19,
      "prevClose": 41.19,
      "updated": "2025-11-07 15:41 ET"
    },
    "HAL": {
      "symbol": "HAL",
      "price": 27.54,
      "prevClose": 27.54,
      "updated": "2025-11-07 15:41 ET"
    },
    "DVN": {
      "symbol": "DVN",
      "price": 33.56,
      "prevClose": 33.56,
      "updated": "2025-11-07 15:41 ET"
    },
    "FANG": {
      "symbol": "FANG",
      "price": 143.5,
      "prevClose": 143.5,
      "updated": "2025-11-07 15:41 ET"
    },
    "WMT": {
      "symbol": "WMT",
      "price": 102.58,
      "prevClose": 102.58,
      "updated": "2025-11-07 15:41 ET"
    },
    "COST": {
      "symbol": "COST",
      "price": 923.64,
      "prevClose": 923.64,
      "updated": "2025-11-07 15:41 ET"
    },
    "HD": {
      "symbol": "HD",
      "price": 370.83,
      "prevClose": 370.83,
      "updated": "2025-11-07 15:41 ET"
    },
    "LOW": {
      "symbol": "LOW",
      "price": 233.2,
      "prevClose": 233.2,
      "updated": "2025-11-07 15:41 ET"
    },
    "TGT": {
      "symbol": "TGT",
      "price": 91.29,
      "prevClose": 91.29,
      "updated": "2025-11-07 15:41 ET"
    },
    "TJX": {
      "symbol": "TJX",
      "price": 144.38,
      "prevClose": 144.38,
      "updated": "2025-11-07 15:41 ET"
    },
    "ROST": {
      "symbol": "ROST",
      "price": 161.17,
      "prevClose": 161.17,
      "updated": "2025-11-07 15:41 ET"
    },
    "DG": {
      "symbol": "DG",
      "price": 99.24,
      "prevClose": 99.24,
      "updated": "2025-11-07 15:41 ET"
    },
    "DLTR": {
      "symbol": "DLTR",
      "price": 105.43,
      "prevClose": 105.43,
      "updated": "2025-11-07 15:41 ET"
    },
    "KR": {
      "symbol": "KR",
      "price": 64.92,
      "prevClose": 64.92,
      "updated": "2025-11-07 15:41 ET"
    },
    "NKE": {
      "symbol": "NKE",
      "price": 61.03,
      "prevClose": 61.03,
      "updated": "2025-11-07 15:41 ET"
    },
    "SBUX": {
      "symbol": "SBUX",
      "price": 85.6,
      "prevClose": 85.6,
      "updated": "2025-11-07 15:41 ET"
    },
    "MCD": {
      "symbol": "MCD",
      "price": 300.14,
      "prevClose": 300.14,
      "updated": "2025-11-07 15:41 ET"
    },
    "CMG": {
      "symbol": "CMG",
      "price": 30.52,
      "prevClose": 30.52,
      "updated": "2025-11-07 15:41 ET"
    },
    "YUM": {
      "symbol": "YUM",
      "price": 149.0,
      "prevClose": 149.0,
      "updated": "2025-11-07 15:41 ET"
    },
    "QSR": {
      "symbol": "QSR",
      "price": 67.76,
      "prevClose": 67.76,
      "updated": "2025-11-07 15:41 ET"
    },
    "WEN": {
      "symbol": "WEN",
      "price": 8.95,
      "prevClose": 8.95,
      "updated": "2025-11-07 15:41 ET"
    },
    "JACK": {
      "symbol": "JACK",
      "price": 16.75,
      "prevClose": 16.75,
      "updated": "2025-11-07 15:41 ET"
    },
    "DPZ": {
      "symbol": "DPZ",
      "price": 410.11,
      "prevClose": 410.11,
      "updated": "2025-11-07 15:41 ET"
    },
    "BA": {
      "symbol": "BA",
      "price": 194.17,
      "prevClose": 194.17,
      "updated": "2025-11-07 15:41 ET"
    },
    "LMT": {
      "symbol": "LMT",
      "price": 459.27,
      "prevClose": 459.27,
      "updated": "2025-11-07 15:41 ET"
    },
    "RTX": {
      "symbol": "RTX",
      "price": 177.32,
      "prevClose": 177.32,
      "updated": "2025-11-07 15:41 ET"
    },
    "GE": {
      "symbol": "GE",
      "price": 307.9,
      "prevClose": 307.9,
      "updated": "2025-11-07 15:41 ET"
    },
    "CAT": {
      "symbol": "CAT",
      "price": 562.15,
      "prevClose": 562.15,
      "updated": "2025-11-07 15:41 ET"
    },
    "DE": {
      "symbol": "DE",
      "price": 467.31,
      "prevClose": 467.31,
      "updated": "2025-11-07 15:41 ET"
    },
    "HON": {
      "symbol": "HON",
      "price": 194.98,
      "prevClose": 194.98,
      "updated": "2025-11-07 15:41 ET"
    },
    "MMM": {
      "symbol": "MMM",
      "price": 164.92,
      "prevClose": 164.92,
      "updated": "2025-11-07 15:41 ET"
    },
    "EMR": {
      "symbol": "EMR",
      "price": 129.15,
      "prevClose": 129.15,
      "updated": "2025-11-07 15:41 ET"
    },
    "ITW": {
      "symbol": "ITW",
      "price": 245.12,
      "prevClose": 245.12,
      "updated": "2025-11-07 15:41 ET"
    },
    "UPS": {
      "symbol": "UPS",
      "price": 96.0,
      "prevClose": 96.0,
      "updated": "2025-11-07 15:41 ET"
    },
    "FDX": {
      "symbol": "FDX",
      "price": 262.5,
      "prevClose": 262.5,
      "updated": "2025-11-07 15:41 ET"
    },
    "DAL": {
      "symbol": "DAL",
      "price": 58.76,
      "prevClose": 58.76,
      "updated": "2025-11-07 15:41 ET"
    },
    "UAL": {
      "symbol": "UAL",
      "price": 97.66,
      "prevClose": 97.66,
      "updated": "2025-11-07 15:41 ET"
    },
    "AAL": {
      "symbol": "AAL",
      "price": 13.6,
      "prevClose": 13.6,
      "updated": "2025-11-07 15:41 ET"
    },
    "LUV": {
      "symbol": "LUV",
      "price": 32.22,
      "prevClose": 32.22,
      "updated": "2025-11-07 15:41 ET"
    },
    "JBLU": {
      "symbol": "JBLU",
      "price": 4.45,
      "prevClose": 4.45,
      "updated": "2025-11-07 15:41 ET"
    },
    "CCL": {
      "symbol": "CCL",
      "price": 26.85,
      "prevClose": 26.85,
      "updated": "2025-11-07 15:41 ET"
    },
    "RCL": {
      "symbol": "RCL",
      "price": 256.25,
      "prevClose": 256.25,
      "updated": "2025-11-07 15:41 ET"
    },
    "NCLH": {
      "symbol": "NCLH",
      "price": 19.1,
      "prevClose": 19.1,
      "updated": "2025-11-07 15:41 ET"
    },
    "MAR": {
      "symbol": "MAR",
      "price": 291.12,
      "prevClose": 291.12,
      "updated": "2025-11-07 15:41 ET"
    },
    "HLT": {
      "symbol": "HLT",
      "price": 273.53,
      "prevClose": 273.53,
      "updated": "2025-11-07 15:41 ET"
    },
    "H": {
      "symbol": "H",
      "price": 154.77,
      "prevClose": 154.77,
      "updated": "2025-11-07 15:41 ET"
    },
    "F": {
      "symbol": "F",
      "price": 13.22,
      "prevClose": 13.22,
      "updated": "2025-11-07 15:41 ET"
    },
    "GM": {
      "symbol": "GM",
      "price": 70.67,
      "prevClose": 70.67,
      "updated": "2025-11-07 15:41 ET"
    },
    "RIVN": {
      "symbol": "RIVN",
      "price": 15.32,
      "prevClose": 15.32,
      "updated": "2025-11-07 15:41 ET"
    },
    "LCID": {
      "symbol": "LCID",
      "price": 17.22,
      "prevClose": 17.22,
      "updated": "2025-11-07 15:41 ET"
    },
    "NIO": {
      "symbol": "NIO",
      "price": 6.86,
      "prevClose": 6.86,
      "updated": "2025-11-07 15:41 ET"
    },
    "XPEV": {
      "symbol": "XPEV",
      "price": 22.5,
      "prevClose": 22.5,
      "updated": "2025-11-07 15:41 ET"
    },
    "LI": {
      "symbol": "LI",
      "price": 19.93,
      "prevClose": 19.93,
      "updated": "2025-11-07 15:41 ET"
    },
    "STLA": {
      "symbol": "STLA",
      "price": 10.22,
      "prevClose": 10.22,
      "updated": "2025-11-07 15:41 ET"
    },
    "TM": {
      "symbol": "TM",
      "price": 202.11,
      "prevClose": 202.11,
      "updated": "2025-11-07 15:41 ET"
    },
    "HMC": {
      "symbol": "HMC",
      "price": 29.83,
      "prevClose": 29.83,
      "updated": "2025-11-07 15:41 ET"
    },
    "PDD": {
      "symbol": "PDD",
      "price": 135.9,
      "prevClose": 135.9,
      "updated": "2025-11-07 15:41 ET"
    },
    "BABA": {
      "symbol": "BABA",
      "price": 165.57,
      "prevClose": 165.57,
      "updated": "2025-11-07 15:41 ET"
    },
    "JD": {
      "symbol": "JD",
      "price": 31.85,
      "prevClose": 31.85,
      "updated": "2025-11-07 15:41 ET"
    },
    "BIDU": {
      "symbol": "BIDU",
      "price": 126.04,
      "prevClose": 126.04,
      "updated": "2025-11-07 15:41 ET"
    },
    "TME": {
      "symbol": "TME",
      "price": 21.25,
      "prevClose": 21.25,
      "updated": "2025-11-07 15:41 ET"
    },
    "BEKE": {
      "symbol": "BEKE",
      "price": 15.51,
      "prevClose": 15.51,
      "updated": "2025-11-07 15:41 ET"
    },
    "BILI": {
      "symbol": "BILI",
      "price": 27.78,
      "prevClose": 27.78,
      "updated": "2025-11-07 15:41 ET"
    },
    "IQ": {
      "symbol": "IQ",
      "price": 2.1,
      "prevClose": 2.1,
      "updated": "2025-11-07 15:41 ET"
    },
    "NTES": {
      "symbol": "NTES",
      "price": 138.89,
      "prevClose": 138.89,
      "updated": "2025-11-07 15:41 ET"
    },
    "T": {
      "symbol": "T",
      "price": 24.72,
      "prevClose": 24.72,
      "updated": "2025-11-07 15:41 ET"
    },
    "VZ": {
      "symbol": "VZ",
      "price": 39.85,
      "prevClose": 39.85,
      "updated": "2025-11-07 15:41 ET"
    },
    "TMUS": {
      "symbol": "TMUS",
      "price": 206.96,
      "prevClose": 206.96,
      "updated": "2025-11-07 15:41 ET"
    },
    "CHTR": {
      "symbol": "CHTR",
      "price": 218.44,
      "prevClose": 218.44,
      "updated": "2025-11-07 15:41 ET"
    },
    "CMCSA": {
      "symbol": "CMCSA",
      "price": 27.31,
      "prevClose": 27.31,
      "updated": "2025-11-07 15:41 ET"
    },
    "PARA": {
      "symbol": "PARA",
      "price": 18.5,
      "prevClose": 18.5,
      "updated": "2025-10-09 16:40 ET"
    },
    "WBD": {
      "symbol": "WBD",
      "price": 22.56,
      "prevClose": 22.56,
      "updated": "2025-11-07 15:41 ET"
    },
    "FOX": {
      "symbol": "FOX",
      "price": 59.47,
      "prevClose": 59.47,
      "updated": "2025-11-07 15:41 ET"
    },
    "EA": {
      "symbol": "EA",
      "price": 200.55,
      "prevClose": 200.55,
      "updated": "2025-11-07 15:41 ET"
    },
    "TTWO": {
      "symbol": "TTWO",
      "price": 231.91,
      "prevClose": 231.91,
      "updated": "2025-11-07 15:41 ET"
    },
    "U": {
      "symbol": "U",
      "price": 39.81,
      "prevClose": 39.81,
      "updated": "2025-11-07 15:41 ET"
    },
    "Z": {
      "symbol": "Z",
      "price": 72.94,
      "prevClose": 72.94,
      "updated": "2025-11-07 15:41 ET"
    },
    "OPEN": {
      "symbol": "OPEN",
      "price": 6.41,
      "prevClose": 6.41,
      "updated": "2025-11-07 15:41 ET"
    },
    "CSGP": {
      "symbol": "CSGP",
      "price": 67.66,
      "prevClose": 67.66,
      "updated": "2025-11-07 15:41 ET"
    },
    "EXPE": {
      "symbol": "EXPE",
      "price": 259.51,
      "prevClose": 259.51,
      "updated": "2025-11-07 15:41 ET"
    },
    "BKNG": {
      "symbol": "BKNG",
      "price": 4915.83,
      "prevClose": 4915.83,
      "updated": "2025-11-07 15:41 ET"
    },
    "LULU": {
      "symbol": "LULU",
      "price": 166.5,
      "prevClose": 166.5,
      "updated": "2025-11-07 15:41 ET"
    },
    "CROX": {
      "symbol": "CROX",
      "price": 78.96,
      "prevClose": 78.96,
      "updated": "2025-11-07 15:41 ET"
    },
    "DECK": {
      "symbol": "DECK",
      "price": 81.89,
      "prevClose": 81.89,
      "updated": "2025-11-07 15:41 ET"
    },
    "UAA": {
      "symbol": "UAA",
      "price": 4.63,
      "prevClose": 4.63,
      "updated": "2025-11-07 15:41 ET"
    },
    "VFC": {
      "symbol": "VFC",
      "price": 14.62,
      "prevClose": 14.62,
      "updated": "2025-11-07 15:41 ET"
    },
    "FUBO": {
      "symbol": "FUBO",
      "price": 3.85,
      "prevClose": 3.85,
      "updated": "2025-11-07 15:41 ET"
    },
    "DDOG": {
      "symbol": "DDOG",
      "price": 190.18,
      "prevClose": 190.18,
      "updated": "2025-11-07 15:41 ET"
    },
    "CRWD": {
      "symbol": "CRWD",
      "price": 538.81,
      "prevClose": 538.81,
      "updated": "2025-11-07 15:41 ET"
    },
    "ZS": {
      "symbol": "ZS",
      "price": 316.54,
      "prevClose": 316.54,
      "updated": "2025-11-07 15:41 ET"
    },
    "OKTA": {
      "symbol": "OKTA",
      "price": 84.89,
      "prevClose": 84.89,
      "updated": "2025-11-07 15:41 ET"
    },
    "PANW": {
      "symbol": "PANW",
      "price": 212.13,
      "prevClose": 212.13,
      "updated": "2025-11-07 15:41 ET"
    },
    "FTNT": {
      "symbol": "FTNT",
      "price": 80.57,
      "prevClose": 80.57,
      "updated": "2025-11-07 15:41 ET"
    },
    "CYBR": {
      "symbol": "CYBR",
      "price": 503.86,
      "prevClose": 503.86,
      "updated": "2025-11-07 15:41 ET"
    },
    "S": {
      "symbol": "S",
      "price": 16.82,
      "prevClose": 16.82,
      "updated": "2025-11-07 15:41 ET"
    },
    "MDB": {
      "symbol": "MDB",
      "price": 360.72,
      "prevClose": 360.72,
      "updated": "2025-11-07 15:41 ET"
    },
    "TEAM": {
      "symbol": "TEAM",
      "price": 157.15,
      "prevClose": 157.15,
      "updated": "2025-11-07 15:41 ET"
    },
    "WDAY": {
      "symbol": "WDAY",
      "price": 223.79,
      "prevClose": 223.79,
      "updated": "2025-11-07 15:41 ET"
    },
    "VEEV": {
      "symbol": "VEEV",
      "price": 294.16,
      "prevClose": 294.16,
      "updated": "2025-11-07 15:41 ET"
    },
    "BILL": {
      "symbol": "BILL",
      "price": 45.56,
      "prevClose": 45.56,
      "updated": "2025-11-07 15:41 ET"
    },
    "AFRM": {
      "symbol": "AFRM",
      "price": 72.81,
      "prevClose": 72.81,
      "updated": "2025-11-07 15:41 ET"
    },
    "UPST": {
      "symbol": "UPST",
      "price": 38.5,
      "prevClose": 38.5,
      "updated": "2025-11-07 15:41 ET"
    },
    "LC": {
      "symbol": "LC",
      "price": 17.99,
      "prevClose": 17.99,
      "updated": "2025-11-07 15:41 ET"
    },
    "NU": {
      "symbol": "NU",
      "price": 15.82,
      "prevClose": 15.82,
      "updated": "2025-11-07 15:41 ET"
    },
    "MELI": {
      "symbol": "MELI",
      "price": 2109.23,
      "prevClose": 2109.23,
      "updated": "2025-11-07 15:41 ET"
    },
    "SE": {
      "symbol": "SE",
      "price": 149.65,
      "prevClose": 149.65,
      "updated": "2025-11-07 15:41 ET"
    },
    "GRAB": {
      "symbol": "GRAB",
      "price": 5.6,
      "prevClose": 5.6,
      "updated": "2025-11-07 15:41 ET"
    },
    "CPNG": {
      "symbol": "CPNG",
      "price": 28.76,
      "prevClose": 28.76,
      "updated": "2025-11-07 15:41 ET"
    },
    "TOST": {
      "symbol": "TOST",
      "price": 36.89,
      "prevClose": 36.89,
      "updated": "2025-11-07 15:41 ET"
    },
    "CHWY": {
      "symbol": "CHWY",
      "price": 33.74,
      "prevClose": 33.74,
      "updated": "2025-11-07 15:41 ET"
    },
    "ETSY": {
      "symbol": "ETSY",
      "price": 58.7,
      "prevClose": 58.7,
      "updated": "2025-11-07 15:41 ET"
    },
    "W": {
      "symbol": "W",
      "price": 107.43,
      "prevClose": 107.43,
      "updated": "2025-11-07 15:41 ET"
    },
    "CVNA": {
      "symbol": "CVNA",
      "price": 303.73,
      "prevClose": 303.73,
      "updated": "2025-11-07 15:41 ET"
    },
    "KMX": {
      "symbol": "KMX",
      "price": 31.98,
      "prevClose": 31.98,
      "updated": "2025-11-07 15:41 ET"
    },
    "AN": {
      "symbol": "AN",
      "price": 192.93,
      "prevClose": 192.93,
      "updated": "2025-11-07 15:41 ET"
    },
    "LAD": {
      "symbol": "LAD",
      "price": 292.89,
      "prevClose": 292.89,
      "updated": "2025-11-07 15:41 ET"
    },
    "ABG": {
      "symbol": "ABG",
      "price": 226.02,
      "prevClose": 226.02,
      "updated": "2025-11-07 15:41 ET"
    },
    "PAG": {
      "symbol": "PAG",
      "price": 158.28,
      "prevClose": 158.28,
      "updated": "2025-11-07 15:41 ET"
    },
    "GES": {
      "symbol": "GES",
      "price": 16.95,
      "prevClose": 16.95,
      "updated": "2025-11-07 15:41 ET"
    },
    "GME": {
      "symbol": "GME",
      "price": 21.49,
      "prevClose": 21.49,
      "updated": "2025-11-07 15:41 ET"
    },
    "AMC": {
      "symbol": "AMC",
      "price": 2.44,
      "prevClose": 2.44,
      "updated": "2025-11-07 15:41 ET"
    },
    "BB": {
      "symbol": "BB",
      "price": 4.53,
      "prevClose": 4.53,
      "updated": "2025-11-07 15:41 ET"
    },
    "BBBY": {
      "symbol": "BBBY",
      "price": 7.05,
      "prevClose": 7.05,
      "updated": "2025-11-07 15:41 ET"
    },
    "KOSS": {
      "symbol": "KOSS",
      "price": 4.53,
      "prevClose": 4.53,
      "updated": "2025-11-07 15:41 ET"
    },
    "SNDL": {
      "symbol": "SNDL",
      "price": 1.77,
      "prevClose": 1.77,
      "updated": "2025-11-07 15:41 ET"
    },
    "CLOV": {
      "symbol": "CLOV",
      "price": 2.61,
      "prevClose": 2.61,
      "updated": "2025-11-07 15:41 ET"
    },
    "WKHS": {
      "symbol": "WKHS",
      "price": 0.78,
      "prevClose": 0.78,
      "updated": "2025-11-07 15:41 ET"
    },
    "SPCE": {
      "symbol": "SPCE",
      "price": 3.55,
      "prevClose": 3.55,
      "updated": "2025-11-07 15:41 ET"
    },
    "SKLZ": {
      "symbol": "SKLZ",
      "price": 6.29,
      "prevClose": 6.29,
      "updated": "2025-11-07 15:41 ET"
    },
    "CLNE": {
      "symbol": "CLNE",
      "price": 2.37,
      "prevClose": 2.37,
      "updated": "2025-11-07 15:41 ET"
    },
    "TLRY": {
      "symbol": "TLRY",
      "price": 1.24,
      "prevClose": 1.24,
      "updated": "2025-11-07 15:41 ET"
    },
    "CGC": {
      "symbol": "CGC",
      "price": 1.18,
      "prevClose": 1.18,
      "updated": "2025-11-07 15:41 ET"
    },
    "ACB": {
      "symbol": "ACB",
      "price": 4.56,
      "prevClose": 4.56,
      "updated": "2025-11-07 15:41 ET"
    },
    "SIRI": {
      "symbol": "SIRI",
      "price": 21.61,
      "prevClose": 21.61,
      "updated": "2025-11-07 15:41 ET"
    },
    "PLUG": {
      "symbol": "PLUG",
      "price": 2.5,
      "prevClose": 2.5,
      "updated": "2025-11-06 15:44 ET"
    },
    "FCEL": {
      "symbol": "FCEL",
      "price": 7.37,
      "prevClose": 7.37,
      "updated": "2025-11-07 15:41 ET"
    },
    "BE": {
      "symbol": "BE",
      "price": 133.44,
      "prevClose": 133.44,
      "updated": "2025-11-07 15:41 ET"
    },
    "QS": {
      "symbol": "QS",
      "price": 16.24,
      "prevClose": 16.24,
      "updated": "2025-11-07 15:41 ET"
    },
    "GOEV": {
      "symbol": "GOEV",
      "price": 0.37,
      "prevClose": 0.37,
      "updated": "2025-11-07 15:41 ET"
    },
    "WOOF": {
      "symbol": "WOOF",
      "price": 3.12,
      "prevClose": 3.12,
      "updated": "2025-11-07 15:41 ET"
    },
    "BARK": {
      "symbol": "BARK",
      "price": 0.79,
      "prevClose": 0.79,
      "updated": "2025-11-07 15:41 ET"
    },
    "CPRI": {
      "symbol": "CPRI",
      "price": 21.97,
      "prevClose": 21.97,
      "updated": "2025-11-07 15:41 ET"
    },
    "BBWI": {
      "symbol": "BBWI",
      "price": 22.81,
      "prevClose": 22.81,
      "updated": "2025-11-07 15:41 ET"
    },
    "PTON": {
      "symbol": "PTON",
      "price": 7.55,
      "prevClose": 7.55,
      "updated": "2025-11-07 15:41 ET"
    },
    "BYND": {
      "symbol": "BYND",
      "price": 1.36,
      "prevClose": 1.36,
      "updated": "2025-11-07 15:41 ET"
    },
    "OUST": {
      "symbol": "OUST",
      "price": 25.61,
      "prevClose": 25.61,
      "updated": "2025-11-07 15:41 ET"
    },
    "LAZR": {
      "symbol": "LAZR",
      "price": 1.25,
      "prevClose": 1.25,
      "updated": "2025-11-07 15:41 ET"
    },
    "LIDR": {
      "symbol": "LIDR",
      "price": 2.34,
      "prevClose": 2.34,
      "updated": "2025-11-07 15:41 ET"
    },
    "JMIA": {
      "symbol": "JMIA",
      "price": 10.91,
      "prevClose": 10.91,
      "updated": "2025-11-07 15:41 ET"
    },
    "VIPS": {
      "symbol": "VIPS",
      "price": 18.66,
      "prevClose": 18.66,
      "updated": "2025-11-07 15:41 ET"
    },
    "BGFV": {
      "symbol": "BGFV",
      "price": 1.44,
      "prevClose": 1.44,
      "updated": "2025-10-03 16:49 ET"
    },
    "PRPL": {
      "symbol": "PRPL",
      "price": 0.84,
      "prevClose": 0.84,
      "updated": "2025-11-07 15:41 ET"
    },
    "CRSR": {
      "symbol": "CRSR",
      "price": 6.57,
      "prevClose": 6.57,
      "updated": "2025-11-07 15:41 ET"
    },
    "APPS": {
      "symbol": "APPS",
      "price": 5.88,
      "prevClose": 5.88,
      "updated": "2025-11-07 15:41 ET"
    },
    "UWMC": {
      "symbol": "UWMC",
      "price": 5.24,
      "prevClose": 5.24,
      "updated": "2025-11-07 15:41 ET"
    },
    "RKT": {
      "symbol": "RKT",
      "price": 16.05,
      "prevClose": 16.05,
      "updated": "2025-11-07 15:41 ET"
    },
    "IONQ": {
      "symbol": "IONQ",
      "price": 57.97,
      "prevClose": 57.97,
      "updated": "2025-11-07 15:41 ET"
    },
    "RGTI": {
      "symbol": "RGTI",
      "price": 33.19,
      "prevClose": 33.19,
      "updated": "2025-11-07 15:41 ET"
    },
    "QUBT": {
      "symbol": "QUBT",
      "price": 12.61,
      "prevClose": 12.61,
      "updated": "2025-11-07 15:41 ET"
    },
    "ARQQ": {
      "symbol": "ARQQ",
      "price": 33.77,
      "prevClose": 33.77,
      "updated": "2025-11-07 15:41 ET"
    },
    "QMCO": {
      "symbol": "QMCO",
      "price": 8.09,
      "prevClose": 8.09,
      "updated": "2025-11-07 15:41 ET"
    },
    "SPY": {
      "symbol": "SPY",
      "price": 669.19,
      "prevClose": 669.19,
      "updated": "2025-11-07 15:41 ET"
    },
    "QQQ": {
      "symbol": "QQQ",
      "price": 607.93,
      "prevClose": 607.93,
      "updated": "2025-11-07 15:41 ET"
    },
    "IWM": {
      "symbol": "IWM",
      "price": 240.8,
      "prevClose": 240.8,
      "updated": "2025-11-07 15:41 ET"
    },
    "DIA": {
      "symbol": "DIA",
      "price": 468.91,
      "prevClose": 468.91,
      "updated": "2025-11-07 15:41 ET"
    },
    "VTI": {
      "symbol": "VTI",
      "price": 329.16,
      "prevClose": 329.16,
      "updated": "2025-11-07 15:41 ET"
    },
    "VOO": {
      "symbol": "VOO",
      "price": 615.27,
      "prevClose": 615.27,
      "updated": "2025-11-07 15:41 ET"
    },
    "ARKK": {
      "symbol": "ARKK",
      "price": 80.42,
      "prevClose": 80.42,
      "updated": "2025-11-07 15:41 ET"
    },
    "ARKG": {
      "symbol": "ARKG",
      "price": 27.83,
      "prevClose": 27.83,
      "updated": "2025-11-07 15:41 ET"
    },
    "ARKW": {
      "symbol": "ARKW",
      "price": 161.89,
      "prevClose": 161.89,
      "updated": "2025-11-07 15:41 ET"
    },
    "ARKF": {
      "symbol": "ARKF",
      "price": 51.66,
      "prevClose": 51.66,
      "updated": "2025-11-07 15:41 ET"
    },
    "GLD": {
      "symbol": "GLD",
      "price": 368.01,
      "prevClose": 368.01,
      "updated": "2025-11-07 15:41 ET"
    },
    "SLV": {
      "symbol": "SLV",
      "price": 43.88,
      "prevClose": 43.88,
      "updated": "2025-11-07 15:41 ET"
    },
    "USO": {
      "symbol": "USO",
      "price": 71.21,
      "prevClose": 71.21,
      "updated": "2025-11-07 15:41 ET"
    },
    "UNG": {
      "symbol": "UNG",
      "price": 13.92,
      "prevClose": 13.92,
      "updated": "2025-11-07 15:41 ET"
    },
    "TLT": {
      "symbol": "TLT",
      "price": 89.61,
      "prevClose": 89.61,
      "updated": "2025-11-07 15:41 ET"
    },
    "HYG": {
      "symbol": "HYG",
      "price": 80.26,
      "prevClose": 80.26,
      "updated": "2025-11-07 15:41 ET"
    },
    "MSTR": {
      "symbol": "MSTR",
      "price": 242.41,
      "prevClose": 242.41,
      "updated": "2025-11-07 15:41 ET"
    },
    "MARA": {
      "symbol": "MARA",
      "price": 15.6,
      "prevClose": 15.6,
      "updated": "2025-11-07 15:41 ET"
    },
    "RIOT": {
      "symbol": "RIOT",
      "price": 16.83,
      "prevClose": 16.83,
      "updated": "2025-11-07 15:41 ET"
    },
    "CLSK": {
      "symbol": "CLSK",
      "price": 15.32,
      "prevClose": 15.32,
      "updated": "2025-11-07 15:41 ET"
    },
    "CIFR": {
      "symbol": "CIFR",
      "price": 20.53,
      "prevClose": 20.53,
      "updated": "2025-11-07 15:41 ET"
    },
    "BITI": {
      "symbol": "BITI",
      "price": 19.97,
      "prevClose": 19.97,
      "updated": "2025-11-07 15:41 ET"
    },
    "SOXL": {
      "symbol": "SOXL",
      "price": 40.46,
      "prevClose": 40.46,
      "updated": "2025-11-07 15:41 ET"
    },
    "TQQQ": {
      "symbol": "TQQQ",
      "price": 104.82,
      "prevClose": 104.82,
      "updated": "2025-11-07 15:41 ET"
    },
    "SQQQ": {
      "symbol": "SQQQ",
      "price": 14.56,
      "prevClose": 14.56,
      "updated": "2025-11-07 15:41 ET"
    },
    "UVXY": {
      "symbol": "UVXY",
      "price": 11.19,
      "prevClose": 11.19,
      "updated": "2025-11-07 15:41 ET"
    },
    "VXX": {
      "symbol": "VXX",
      "price": 35.17,
      "prevClose": 35.17,
      "updated": "2025-11-07 15:41 ET"
    }
  }
}