{
  "updated": "2026-05-05 17:36 ET",
  "stocks": {
    "AAPL": {
      "symbol": "AAPL",
      "price": 284.18,
      "prevClose": 276.83,
      "updated": "2026-05-05 17:36 ET"
    },
    "MSFT": {
      "symbol": "MSFT",
      "price": 411.38,
      "prevClose": 413.62,
      "updated": "2026-05-05 17:36 ET"
    },
    "GOOGL": {
      "symbol": "GOOGL",
      "price": 388.43,
      "prevClose": 383.25,
      "updated": "2026-05-05 17:36 ET"
    },
    "AMZN": {
      "symbol": "AMZN",
      "price": 273.55,
      "prevClose": 272.05,
      "updated": "2026-05-05 17:36 ET"
    },
    "TSLA": {
      "symbol": "TSLA",
      "price": 389.37,
      "prevClose": 392.51,
      "updated": "2026-05-05 17:36 ET"
    },
    "META": {
      "symbol": "META",
      "price": 604.96,
      "prevClose": 610.41,
      "updated": "2026-05-05 17:36 ET"
    },
    "NVDA": {
      "symbol": "NVDA",
      "price": 196.5,
      "prevClose": 198.48,
      "updated": "2026-05-05 17:36 ET"
    },
    "AMD": {
      "symbol": "AMD",
      "price": 355.26,
      "prevClose": 341.54,
      "updated": "2026-05-05 17:36 ET"
    },
    "NFLX": {
      "symbol": "NFLX",
      "price": 87.89,
      "prevClose": 91.02,
      "updated": "2026-05-05 17:36 ET"
    },
    "DIS": {
      "symbol": "DIS",
      "price": 100.48,
      "prevClose": 101.31,
      "updated": "2026-05-05 17:36 ET"
    },
    "PYPL": {
      "symbol": "PYPL",
      "price": 46.49,
      "prevClose": 50.39,
      "updated": "2026-05-05 17:36 ET"
    },
    "XYZ": {
      "symbol": "XYZ",
      "price": 71.25,
      "prevClose": 71.9,
      "updated": "2026-05-05 17:36 ET"
    },
    "COIN": {
      "symbol": "COIN",
      "price": 197.75,
      "prevClose": 202.99,
      "updated": "2026-05-05 17:36 ET"
    },
    "SHOP": {
      "symbol": "SHOP",
      "price": 107.63,
      "prevClose": 127.55,
      "updated": "2026-05-05 17:36 ET"
    },
    "UBER": {
      "symbol": "UBER",
      "price": 72.95,
      "prevClose": 73.93,
      "updated": "2026-05-05 17:36 ET"
    },
    "LYFT": {
      "symbol": "LYFT",
      "price": 14.09,
      "prevClose": 14.06,
      "updated": "2026-05-05 17:36 ET"
    },
    "SNAP": {
      "symbol": "SNAP",
      "price": 6.11,
      "prevClose": 6.17,
      "updated": "2026-05-05 17:36 ET"
    },
    "SPOT": {
      "symbol": "SPOT",
      "price": 419.53,
      "prevClose": 438.26,
      "updated": "2026-05-05 17:36 ET"
    },
    "RBLX": {
      "symbol": "RBLX",
      "price": 44.04,
      "prevClose": 47.57,
      "updated": "2026-05-05 17:36 ET"
    },
    "ROKU": {
      "symbol": "ROKU",
      "price": 124.41,
      "prevClose": 126.02,
      "updated": "2026-05-05 17:36 ET"
    },
    "HOOD": {
      "symbol": "HOOD",
      "price": 77.03,
      "prevClose": 76.55,
      "updated": "2026-05-05 17:36 ET"
    },
    "SOFI": {
      "symbol": "SOFI",
      "price": 16.02,
      "prevClose": 16.2,
      "updated": "2026-05-05 17:36 ET"
    },
    "PLTR": {
      "symbol": "PLTR",
      "price": 135.91,
      "prevClose": 146.03,
      "updated": "2026-05-05 17:36 ET"
    },
    "ABNB": {
      "symbol": "ABNB",
      "price": 139.73,
      "prevClose": 138.86,
      "updated": "2026-05-05 17:36 ET"
    },
    "DASH": {
      "symbol": "DASH",
      "price": 166.14,
      "prevClose": 172.57,
      "updated": "2026-05-05 17:36 ET"
    },
    "SNOW": {
      "symbol": "SNOW",
      "price": 141.71,
      "prevClose": 144.21,
      "updated": "2026-05-05 17:36 ET"
    },
    "NET": {
      "symbol": "NET",
      "price": 244.43,
      "prevClose": 224.17,
      "updated": "2026-05-05 17:36 ET"
    },
    "DKNG": {
      "symbol": "DKNG",
      "price": 24.17,
      "prevClose": 23.57,
      "updated": "2026-05-05 17:36 ET"
    },
    "PINS": {
      "symbol": "PINS",
      "price": 22.28,
      "prevClose": 20.85,
      "updated": "2026-05-05 17:36 ET"
    },
    "TWLO": {
      "symbol": "TWLO",
      "price": 195.58,
      "prevClose": 189.67,
      "updated": "2026-05-05 17:36 ET"
    },
    "ZM": {
      "symbol": "ZM",
      "price": 109.1,
      "prevClose": 106.63,
      "updated": "2026-05-05 17:36 ET"
    },
    "DOCU": {
      "symbol": "DOCU",
      "price": 48.38,
      "prevClose": 48.45,
      "updated": "2026-05-05 17:36 ET"
    },
    "CRM": {
      "symbol": "CRM",
      "price": 186.99,
      "prevClose": 185.48,
      "updated": "2026-05-05 17:36 ET"
    },
    "ORCL": {
      "symbol": "ORCL",
      "price": 185.35,
      "prevClose": 180.29,
      "updated": "2026-05-05 17:36 ET"
    },
    "INTC": {
      "symbol": "INTC",
      "price": 108.15,
      "prevClose": 95.78,
      "updated": "2026-05-05 17:36 ET"
    },
    "IBM": {
      "symbol": "IBM",
      "price": 229.03,
      "prevClose": 229.48,
      "updated": "2026-05-05 17:36 ET"
    },
    "CSCO": {
      "symbol": "CSCO",
      "price": 94.3,
      "prevClose": 92.63,
      "updated": "2026-05-05 17:36 ET"
    },
    "ADBE": {
      "symbol": "ADBE",
      "price": 255.62,
      "prevClose": 253.96,
      "updated": "2026-05-05 17:36 ET"
    },
    "NOW": {
      "symbol": "NOW",
      "price": 92.01,
      "prevClose": 91.97,
      "updated": "2026-05-05 17:36 ET"
    },
    "INTU": {
      "symbol": "INTU",
      "price": 398.32,
      "prevClose": 406.99,
      "updated": "2026-05-05 17:36 ET"
    },
    "TXN": {
      "symbol": "TXN",
      "price": 281.0,
      "prevClose": 280.89,
      "updated": "2026-05-05 17:36 ET"
    },
    "QCOM": {
      "symbol": "QCOM",
      "price": 186.55,
      "prevClose": 168.38,
      "updated": "2026-05-05 17:36 ET"
    },
    "AVGO": {
      "symbol": "AVGO",
      "price": 427.36,
      "prevClose": 416.5,
      "updated": "2026-05-05 17:36 ET"
    },
    "MU": {
      "symbol": "MU",
      "price": 640.2,
      "prevClose": 576.45,
      "updated": "2026-05-05 17:36 ET"
    },
    "AMAT": {
      "symbol": "AMAT",
      "price": 410.82,
      "prevClose": 391.38,
      "updated": "2026-05-05 17:36 ET"
    },
    "LRCX": {
      "symbol": "LRCX",
      "price": 275.8,
      "prevClose": 258.57,
      "updated": "2026-05-05 17:36 ET"
    },
    "KLAC": {
      "symbol": "KLAC",
      "price": 1732.9,
      "prevClose": 1713.32,
      "updated": "2026-05-05 17:36 ET"
    },
    "MRVL": {
      "symbol": "MRVL",
      "price": 168.75,
      "prevClose": 163.66,
      "updated": "2026-05-05 17:36 ET"
    },
    "ON": {
      "symbol": "ON",
      "price": 102.67,
      "prevClose": 102.04,
      "updated": "2026-05-05 17:36 ET"
    },
    "ARM": {
      "symbol": "ARM",
      "price": 208.84,
      "prevClose": 203.26,
      "updated": "2026-05-05 17:36 ET"
    },
    "SMCI": {
      "symbol": "SMCI",
      "price": 27.83,
      "prevClose": 27.92,
      "updated": "2026-05-05 17:36 ET"
    },
    "DELL": {
      "symbol": "DELL",
      "price": 216.32,
      "prevClose": 211.64,
      "updated": "2026-05-05 17:36 ET"
    },
    "HPE": {
      "symbol": "HPE",
      "price": 30.04,
      "prevClose": 28.71,
      "updated": "2026-05-05 17:36 ET"
    },
    "WDC": {
      "symbol": "WDC",
      "price": 465.26,
      "prevClose": 442.36,
      "updated": "2026-05-05 17:36 ET"
    },
    "STX": {
      "symbol": "STX",
      "price": 771.01,
      "prevClose": 738.54,
      "updated": "2026-05-05 17:36 ET"
    },
    "PSTG": {
      "symbol": "PSTG",
      "price": 72.75,
      "prevClose": 72.75,
      "updated": "2026-05-05 17:36 ET"
    },
    "JPM": {
      "symbol": "JPM",
      "price": 309.4,
      "prevClose": 307.65,
      "updated": "2026-05-05 17:36 ET"
    },
    "BAC": {
      "symbol": "BAC",
      "price": 53.12,
      "prevClose": 52.19,
      "updated": "2026-05-05 17:36 ET"
    },
    "WFC": {
      "symbol": "WFC",
      "price": 79.89,
      "prevClose": 79.18,
      "updated": "2026-05-05 17:36 ET"
    },
    "GS": {
      "symbol": "GS",
      "price": 918.89,
      "prevClose": 903.27,
      "updated": "2026-05-05 17:36 ET"
    },
    "MS": {
      "symbol": "MS",
      "price": 189.25,
      "prevClose": 188.01,
      "updated": "2026-05-05 17:36 ET"
    },
    "C": {
      "symbol": "C",
      "price": 128.01,
      "prevClose": 125.63,
      "updated": "2026-05-05 17:36 ET"
    },
    "BLK": {
      "symbol": "BLK",
      "price": 1048.91,
      "prevClose": 1052.25,
      "updated": "2026-05-05 17:36 ET"
    },
    "SCHW": {
      "symbol": "SCHW",
      "price": 92.4,
      "prevClose": 91.48,
      "updated": "2026-05-05 17:36 ET"
    },
    "AXP": {
      "symbol": "AXP",
      "price": 315.95,
      "prevClose": 319.21,
      "updated": "2026-05-05 17:36 ET"
    },
    "V": {
      "symbol": "V",
      "price": 322.03,
      "prevClose": 326.85,
      "updated": "2026-05-05 17:36 ET"
    },
    "MA": {
      "symbol": "MA",
      "price": 497.08,
      "prevClose": 504.74,
      "updated": "2026-05-05 17:36 ET"
    },
    "COF": {
      "symbol": "COF",
      "price": 189.68,
      "prevClose": 189.92,
      "updated": "2026-05-05 17:36 ET"
    },
    "SYF": {
      "symbol": "SYF",
      "price": 73.78,
      "prevClose": 74.24,
      "updated": "2026-05-05 17:36 ET"
    },
    "ALLY": {
      "symbol": "ALLY",
      "price": 43.21,
      "prevClose": 43.03,
      "updated": "2026-05-05 17:36 ET"
    },
    "JNJ": {
      "symbol": "JNJ",
      "price": 225.55,
      "prevClose": 224.2,
      "updated": "2026-05-05 17:36 ET"
    },
    "UNH": {
      "symbol": "UNH",
      "price": 363.87,
      "prevClose": 370.75,
      "updated": "2026-05-05 17:36 ET"
    },
    "PFE": {
      "symbol": "PFE",
      "price": 26.45,
      "prevClose": 26.3,
      "updated": "2026-05-05 17:36 ET"
    },
    "ABBV": {
      "symbol": "ABBV",
      "price": 206.11,
      "prevClose": 208.16,
      "updated": "2026-05-05 17:36 ET"
    },
    "TMO": {
      "symbol": "TMO",
      "price": 466.76,
      "prevClose": 462.6,
      "updated": "2026-05-05 17:36 ET"
    },
    "ABT": {
      "symbol": "ABT",
      "price": 87.17,
      "prevClose": 87.54,
      "updated": "2026-05-05 17:36 ET"
    },
    "DHR": {
      "symbol": "DHR",
      "price": 174.63,
      "prevClose": 174.04,
      "updated": "2026-05-05 17:36 ET"
    },
    "LLY": {
      "symbol": "LLY",
      "price": 988.87,
      "prevClose": 967.93,
      "updated": "2026-05-05 17:36 ET"
    },
    "MRK": {
      "symbol": "MRK",
      "price": 113.15,
      "prevClose": 113.11,
      "updated": "2026-05-05 17:36 ET"
    },
    "BMY": {
      "symbol": "BMY",
      "price": 56.95,
      "prevClose": 57.38,
      "updated": "2026-05-05 17:36 ET"
    },
    "AMGN": {
      "symbol": "AMGN",
      "price": 329.59,
      "prevClose": 323.85,
      "updated": "2026-05-05 17:36 ET"
    },
    "GILD": {
      "symbol": "GILD",
      "price": 133.48,
      "prevClose": 132.69,
      "updated": "2026-05-05 17:36 ET"
    },
    "VRTX": {
      "symbol": "VRTX",
      "price": 424.36,
      "prevClose": 429.85,
      "updated": "2026-05-05 17:36 ET"
    },
    "BIIB": {
      "symbol": "BIIB",
      "price": 189.13,
      "prevClose": 187.21,
      "updated": "2026-05-05 17:36 ET"
    },
    "REGN": {
      "symbol": "REGN",
      "price": 702.27,
      "prevClose": 709.21,
      "updated": "2026-05-05 17:36 ET"
    },
    "MRNA": {
      "symbol": "MRNA",
      "price": 46.71,
      "prevClose": 47.3,
      "updated": "2026-05-05 17:36 ET"
    },
    "BNTX": {
      "symbol": "BNTX",
      "price": 95.5,
      "prevClose": 99.35,
      "updated": "2026-05-05 17:36 ET"
    },
    "NVAX": {
      "symbol": "NVAX",
      "price": 8.1,
      "prevClose": 8.03,
      "updated": "2026-05-05 17:36 ET"
    },
    "XOM": {
      "symbol": "XOM",
      "price": 154.88,
      "prevClose": 153.69,
      "updated": "2026-05-05 17:36 ET"
    },
    "CVX": {
      "symbol": "CVX",
      "price": 192.64,
      "prevClose": 192.28,
      "updated": "2026-05-05 17:36 ET"
    },
    "COP": {
      "symbol": "COP",
      "price": 123.32,
      "prevClose": 124.91,
      "updated": "2026-05-05 17:36 ET"
    },
    "SLB": {
      "symbol": "SLB",
      "price": 56.0,
      "prevClose": 55.63,
      "updated": "2026-05-05 17:36 ET"
    },
    "EOG": {
      "symbol": "EOG",
      "price": 140.82,
      "prevClose": 141.61,
      "updated": "2026-05-05 17:36 ET"
    },
    "MPC": {
      "symbol": "MPC",
      "price": 260.51,
      "prevClose": 252.54,
      "updated": "2026-05-05 17:36 ET"
    },
    "VLO": {
      "symbol": "VLO",
      "price": 253.45,
      "prevClose": 251.63,
      "updated": "2026-05-05 17:36 ET"
    },
    "PSX": {
      "symbol": "PSX",
      "price": 180.26,
      "prevClose": 178.47,
      "updated": "2026-05-05 17:36 ET"
    },
    "OXY": {
      "symbol": "OXY",
      "price": 59.34,
      "prevClose": 60.27,
      "updated": "2026-05-05 17:36 ET"
    },
    "HAL": {
      "symbol": "HAL",
      "price": 41.72,
      "prevClose": 41.98,
      "updated": "2026-05-05 17:36 ET"
    },
    "DVN": {
      "symbol": "DVN",
      "price": 50.99,
      "prevClose": 51.26,
      "updated": "2026-05-05 17:36 ET"
    },
    "FANG": {
      "symbol": "FANG",
      "price": 206.18,
      "prevClose": 213.69,
      "updated": "2026-05-05 17:36 ET"
    },
    "WMT": {
      "symbol": "WMT",
      "price": 130.79,
      "prevClose": 130.33,
      "updated": "2026-05-05 17:36 ET"
    },
    "COST": {
      "symbol": "COST",
      "price": 1016.42,
      "prevClose": 1012.79,
      "updated": "2026-05-05 17:36 ET"
    },
    "HD": {
      "symbol": "HD",
      "price": 315.42,
      "prevClose": 312.42,
      "updated": "2026-05-05 17:36 ET"
    },
    "LOW": {
      "symbol": "LOW",
      "price": 225.23,
      "prevClose": 223.72,
      "updated": "2026-05-05 17:36 ET"
    },
    "TGT": {
      "symbol": "TGT",
      "price": 128.82,
      "prevClose": 127.76,
      "updated": "2026-05-05 17:36 ET"
    },
    "TJX": {
      "symbol": "TJX",
      "price": 154.96,
      "prevClose": 154.64,
      "updated": "2026-05-05 17:36 ET"
    },
    "ROST": {
      "symbol": "ROST",
      "price": 227.42,
      "prevClose": 226.02,
      "updated": "2026-05-05 17:36 ET"
    },
    "DG": {
      "symbol": "DG",
      "price": 117.01,
      "prevClose": 114.48,
      "updated": "2026-05-05 17:36 ET"
    },
    "DLTR": {
      "symbol": "DLTR",
      "price": 93.69,
      "prevClose": 94.05,
      "updated": "2026-05-05 17:36 ET"
    },
    "KR": {
      "symbol": "KR",
      "price": 66.92,
      "prevClose": 67.55,
      "updated": "2026-05-05 17:36 ET"
    },
    "NKE": {
      "symbol": "NKE",
      "price": 43.06,
      "prevClose": 43.09,
      "updated": "2026-05-05 17:36 ET"
    },
    "SBUX": {
      "symbol": "SBUX",
      "price": 104.94,
      "prevClose": 104.97,
      "updated": "2026-05-05 17:36 ET"
    },
    "MCD": {
      "symbol": "MCD",
      "price": 285.17,
      "prevClose": 284.1,
      "updated": "2026-05-05 17:36 ET"
    },
    "CMG": {
      "symbol": "CMG",
      "price": 32.31,
      "prevClose": 31.98,
      "updated": "2026-05-05 17:36 ET"
    },
    "YUM": {
      "symbol": "YUM",
      "price": 153.89,
      "prevClose": 154.4,
      "updated": "2026-05-05 17:36 ET"
    },
    "QSR": {
      "symbol": "QSR",
      "price": 81.67,
      "prevClose": 80.05,
      "updated": "2026-05-05 17:36 ET"
    },
    "WEN": {
      "symbol": "WEN",
      "price": 6.61,
      "prevClose": 6.54,
      "updated": "2026-05-05 17:36 ET"
    },
    "JACK": {
      "symbol": "JACK",
      "price": 12.84,
      "prevClose": 12.05,
      "updated": "2026-05-05 17:36 ET"
    },
    "DPZ": {
      "symbol": "DPZ",
      "price": 331.73,
      "prevClose": 330.42,
      "updated": "2026-05-05 17:36 ET"
    },
    "BA": {
      "symbol": "BA",
      "price": 224.38,
      "prevClose": 221.3,
      "updated": "2026-05-05 17:36 ET"
    },
    "LMT": {
      "symbol": "LMT",
      "price": 508.93,
      "prevClose": 518.15,
      "updated": "2026-05-05 17:36 ET"
    },
    "RTX": {
      "symbol": "RTX",
      "price": 172.87,
      "prevClose": 172.9,
      "updated": "2026-05-05 17:36 ET"
    },
    "GE": {
      "symbol": "GE",
      "price": 286.68,
      "prevClose": 280.52,
      "updated": "2026-05-05 17:36 ET"
    },
    "CAT": {
      "symbol": "CAT",
      "price": 904.59,
      "prevClose": 874.78,
      "updated": "2026-05-05 17:36 ET"
    },
    "DE": {
      "symbol": "DE",
      "price": 575.79,
      "prevClose": 578.39,
      "updated": "2026-05-05 17:36 ET"
    },
    "HON": {
      "symbol": "HON",
      "price": 209.06,
      "prevClose": 209.59,
      "updated": "2026-05-05 17:36 ET"
    },
    "MMM": {
      "symbol": "MMM",
      "price": 142.82,
      "prevClose": 141.56,
      "updated": "2026-05-05 17:36 ET"
    },
    "EMR": {
      "symbol": "EMR",
      "price": 138.38,
      "prevClose": 135.46,
      "updated": "2026-05-05 17:36 ET"
    },
    "ITW": {
      "symbol": "ITW",
      "price": 254.55,
      "prevClose": 251.65,
      "updated": "2026-05-05 17:36 ET"
    },
    "UPS": {
      "symbol": "UPS",
      "price": 98.07,
      "prevClose": 96.31,
      "updated": "2026-05-05 17:36 ET"
    },
    "FDX": {
      "symbol": "FDX",
      "price": 362.75,
      "prevClose": 357.8,
      "updated": "2026-05-05 17:36 ET"
    },
    "DAL": {
      "symbol": "DAL",
      "price": 70.86,
      "prevClose": 68.5,
      "updated": "2026-05-05 17:36 ET"
    },
    "UAL": {
      "symbol": "UAL",
      "price": 93.67,
      "prevClose": 90.07,
      "updated": "2026-05-05 17:36 ET"
    },
    "AAL": {
      "symbol": "AAL",
      "price": 12.37,
      "prevClose": 11.81,
      "updated": "2026-05-05 17:36 ET"
    },
    "LUV": {
      "symbol": "LUV",
      "price": 39.71,
      "prevClose": 38.35,
      "updated": "2026-05-05 17:36 ET"
    },
    "JBLU": {
      "symbol": "JBLU",
      "price": 4.84,
      "prevClose": 4.79,
      "updated": "2026-05-05 17:36 ET"
    },
    "CCL": {
      "symbol": "CCL",
      "price": 25.77,
      "prevClose": 25.67,
      "updated": "2026-05-05 17:36 ET"
    },
    "RCL": {
      "symbol": "RCL",
      "price": 263.98,
      "prevClose": 259.48,
      "updated": "2026-05-05 17:36 ET"
    },
    "NCLH": {
      "symbol": "NCLH",
      "price": 16.94,
      "prevClose": 17.2,
      "updated": "2026-05-05 17:36 ET"
    },
    "MAR": {
      "symbol": "MAR",
      "price": 354.52,
      "prevClose": 347.24,
      "updated": "2026-05-05 17:36 ET"
    },
    "HLT": {
      "symbol": "HLT",
      "price": 312.77,
      "prevClose": 311.38,
      "updated": "2026-05-05 17:36 ET"
    },
    "H": {
      "symbol": "H",
      "price": 161.98,
      "prevClose": 159.12,
      "updated": "2026-05-05 17:36 ET"
    },
    "F": {
      "symbol": "F",
      "price": 11.69,
      "prevClose": 11.5,
      "updated": "2026-05-05 17:36 ET"
    },
    "GM": {
      "symbol": "GM",
      "price": 76.15,
      "prevClose": 75.7,
      "updated": "2026-05-05 17:36 ET"
    },
    "RIVN": {
      "symbol": "RIVN",
      "price": 14.6,
      "prevClose": 14.51,
      "updated": "2026-05-05 17:36 ET"
    },
    "LCID": {
      "symbol": "LCID",
      "price": 6.25,
      "prevClose": 6.69,
      "updated": "2026-05-05 17:36 ET"
    },
    "NIO": {
      "symbol": "NIO",
      "price": 5.9,
      "prevClose": 6.07,
      "updated": "2026-05-05 17:36 ET"
    },
    "XPEV": {
      "symbol": "XPEV",
      "price": 15.82,
      "prevClose": 15.98,
      "updated": "2026-05-05 17:36 ET"
    },
    "LI": {
      "symbol": "LI",
      "price": 17.78,
      "prevClose": 17.88,
      "updated": "2026-05-05 17:36 ET"
    },
    "STLA": {
      "symbol": "STLA",
      "price": 7.2,
      "prevClose": 7.08,
      "updated": "2026-05-05 17:36 ET"
    },
    "TM": {
      "symbol": "TM",
      "price": 189.99,
      "prevClose": 188.3,
      "updated": "2026-05-05 17:36 ET"
    },
    "HMC": {
      "symbol": "HMC",
      "price": 24.16,
      "prevClose": 23.86,
      "updated": "2026-05-05 17:36 ET"
    },
    "PDD": {
      "symbol": "PDD",
      "price": 96.75,
      "prevClose": 97.79,
      "updated": "2026-05-05 17:36 ET"
    },
    "BABA": {
      "symbol": "BABA",
      "price": 132.26,
      "prevClose": 133.27,
      "updated": "2026-05-05 17:36 ET"
    },
    "JD": {
      "symbol": "JD",
      "price": 29.68,
      "prevClose": 30.04,
      "updated": "2026-05-05 17:36 ET"
    },
    "BIDU": {
      "symbol": "BIDU",
      "price": 126.24,
      "prevClose": 127.48,
      "updated": "2026-05-05 17:36 ET"
    },
    "TME": {
      "symbol": "TME",
      "price": 9.16,
      "prevClose": 9.14,
      "updated": "2026-05-05 17:36 ET"
    },
    "BEKE": {
      "symbol": "BEKE",
      "price": 18.13,
      "prevClose": 17.46,
      "updated": "2026-05-05 17:36 ET"
    },
    "BILI": {
      "symbol": "BILI",
      "price": 21.55,
      "prevClose": 21.69,
      "updated": "2026-05-05 17:36 ET"
    },
    "IQ": {
      "symbol": "IQ",
      "price": 1.2,
      "prevClose": 1.25,
      "updated": "2026-05-05 17:36 ET"
    },
    "NTES": {
      "symbol": "NTES",
      "price": 115.1,
      "prevClose": 116.25,
      "updated": "2026-05-05 17:36 ET"
    },
    "T": {
      "symbol": "T",
      "price": 25.9,
      "prevClose": 26.1,
      "updated": "2026-05-05 17:36 ET"
    },
    "VZ": {
      "symbol": "VZ",
      "price": 47.34,
      "prevClose": 47.57,
      "updated": "2026-05-05 17:36 ET"
    },
    "TMUS": {
      "symbol": "TMUS",
      "price": 194.31,
      "prevClose": 194.42,
      "updated": "2026-05-05 17:36 ET"
    },
    "CHTR": {
      "symbol": "CHTR",
      "price": 158.23,
      "prevClose": 165.34,
      "updated": "2026-05-05 17:36 ET"
    },
    "CMCSA": {
      "symbol": "CMCSA",
      "price": 26.46,
      "prevClose": 27.07,
      "updated": "2026-05-05 17:36 ET"
    },
    "PARA": {
      "symbol": "PARA",
      "price": 18.5,
      "prevClose": 18.5,
      "updated": "2025-10-09 16:40 ET"
    },
    "WBD": {
      "symbol": "WBD",
      "price": 27.22,
      "prevClose": 26.96,
      "updated": "2026-05-05 17:36 ET"
    },
    "FOX": {
      "symbol": "FOX",
      "price": 55.91,
      "prevClose": 56.07,
      "updated": "2026-05-05 17:36 ET"
    },
    "EA": {
      "symbol": "EA",
      "price": 201.57,
      "prevClose": 201.82,
      "updated": "2026-05-05 17:36 ET"
    },
    "TTWO": {
      "symbol": "TTWO",
      "price": 223.11,
      "prevClose": 225.18,
      "updated": "2026-05-05 17:36 ET"
    },
    "U": {
      "symbol": "U",
      "price": 27.34,
      "prevClose": 27.72,
      "updated": "2026-05-05 17:36 ET"
    },
    "Z": {
      "symbol": "Z",
      "price": 43.54,
      "prevClose": 44.03,
      "updated": "2026-05-05 17:36 ET"
    },
    "OPEN": {
      "symbol": "OPEN",
      "price": 5.23,
      "prevClose": 5.13,
      "updated": "2026-05-05 17:36 ET"
    },
    "CSGP": {
      "symbol": "CSGP",
      "price": 34.9,
      "prevClose": 35.38,
      "updated": "2026-05-05 17:36 ET"
    },
    "EXPE": {
      "symbol": "EXPE",
      "price": 248.65,
      "prevClose": 246.5,
      "updated": "2026-05-05 17:36 ET"
    },
    "BKNG": {
      "symbol": "BKNG",
      "price": 167.63,
      "prevClose": 165.58,
      "updated": "2026-05-05 17:36 ET"
    },
    "LULU": {
      "symbol": "LULU",
      "price": 130.21,
      "prevClose": 128.98,
      "updated": "2026-05-05 17:36 ET"
    },
    "CROX": {
      "symbol": "CROX",
      "price": 102.94,
      "prevClose": 101.48,
      "updated": "2026-05-05 17:36 ET"
    },
    "DECK": {
      "symbol": "DECK",
      "price": 98.54,
      "prevClose": 97.65,
      "updated": "2026-05-05 17:36 ET"
    },
    "UAA": {
      "symbol": "UAA",
      "price": 6.27,
      "prevClose": 6.08,
      "updated": "2026-05-05 17:36 ET"
    },
    "VFC": {
      "symbol": "VFC",
      "price": 18.32,
      "prevClose": 18.39,
      "updated": "2026-05-05 17:36 ET"
    },
    "FUBO": {
      "symbol": "FUBO",
      "price": 12.4,
      "prevClose": 12.85,
      "updated": "2026-05-05 17:36 ET"
    },
    "DDOG": {
      "symbol": "DDOG",
      "price": 145.73,
      "prevClose": 146.69,
      "updated": "2026-05-05 17:36 ET"
    },
    "CRWD": {
      "symbol": "CRWD",
      "price": 476.53,
      "prevClose": 469.24,
      "updated": "2026-05-05 17:36 ET"
    },
    "ZS": {
      "symbol": "ZS",
      "price": 141.36,
      "prevClose": 142.2,
      "updated": "2026-05-05 17:36 ET"
    },
    "OKTA": {
      "symbol": "OKTA",
      "price": 77.75,
      "prevClose": 77.24,
      "updated": "2026-05-05 17:36 ET"
    },
    "PANW": {
      "symbol": "PANW",
      "price": 183.98,
      "prevClose": 184.56,
      "updated": "2026-05-05 17:36 ET"
    },
    "FTNT": {
      "symbol": "FTNT",
      "price": 89.92,
      "prevClose": 89.24,
      "updated": "2026-05-05 17:36 ET"
    },
    "CYBR": {
      "symbol": "CYBR",
      "price": 408.85,
      "prevClose": 408.85,
      "updated": "2026-02-17 16:04 ET"
    },
    "S": {
      "symbol": "S",
      "price": 15.86,
      "prevClose": 15.6,
      "updated": "2026-05-05 17:36 ET"
    },
    "MDB": {
      "symbol": "MDB",
      "price": 266.68,
      "prevClose": 264.69,
      "updated": "2026-05-05 17:36 ET"
    },
    "TEAM": {
      "symbol": "TEAM",
      "price": 92.35,
      "prevClose": 93.16,
      "updated": "2026-05-05 17:36 ET"
    },
    "WDAY": {
      "symbol": "WDAY",
      "price": 128.88,
      "prevClose": 127.89,
      "updated": "2026-05-05 17:36 ET"
    },
    "VEEV": {
      "symbol": "VEEV",
      "price": 171.19,
      "prevClose": 170.22,
      "updated": "2026-05-05 17:36 ET"
    },
    "BILL": {
      "symbol": "BILL",
      "price": 38.32,
      "prevClose": 39.72,
      "updated": "2026-05-05 17:36 ET"
    },
    "AFRM": {
      "symbol": "AFRM",
      "price": 66.81,
      "prevClose": 67.08,
      "updated": "2026-05-05 17:36 ET"
    },
    "UPST": {
      "symbol": "UPST",
      "price": 31.17,
      "prevClose": 32.08,
      "updated": "2026-05-05 17:36 ET"
    },
    "LC": {
      "symbol": "LC",
      "price": 17.07,
      "prevClose": 16.64,
      "updated": "2026-05-05 17:36 ET"
    },
    "NU": {
      "symbol": "NU",
      "price": 14.25,
      "prevClose": 14.16,
      "updated": "2026-05-05 17:36 ET"
    },
    "MELI": {
      "symbol": "MELI",
      "price": 1817.31,
      "prevClose": 1813.53,
      "updated": "2026-05-05 17:36 ET"
    },
    "SE": {
      "symbol": "SE",
      "price": 84.48,
      "prevClose": 85.41,
      "updated": "2026-05-05 17:36 ET"
    },
    "GRAB": {
      "symbol": "GRAB",
      "price": 3.68,
      "prevClose": 3.62,
      "updated": "2026-05-05 17:36 ET"
    },
    "CPNG": {
      "symbol": "CPNG",
      "price": 20.76,
      "prevClose": 20.26,
      "updated": "2026-05-05 17:36 ET"
    },
    "TOST": {
      "symbol": "TOST",
      "price": 28.54,
      "prevClose": 29.41,
      "updated": "2026-05-05 17:36 ET"
    },
    "CHWY": {
      "symbol": "CHWY",
      "price": 24.54,
      "prevClose": 24.56,
      "updated": "2026-05-05 17:36 ET"
    },
    "ETSY": {
      "symbol": "ETSY",
      "price": 62.95,
      "prevClose": 64.04,
      "updated": "2026-05-05 17:36 ET"
    },
    "W": {
      "symbol": "W",
      "price": 63.2,
      "prevClose": 64.85,
      "updated": "2026-05-05 17:36 ET"
    },
    "CVNA": {
      "symbol": "CVNA",
      "price": 379.09,
      "prevClose": 376.55,
      "updated": "2026-05-05 17:36 ET"
    },
    "KMX": {
      "symbol": "KMX",
      "price": 37.25,
      "prevClose": 36.88,
      "updated": "2026-05-05 17:36 ET"
    },
    "AN": {
      "symbol": "AN",
      "price": 202.29,
      "prevClose": 202.66,
      "updated": "2026-05-05 17:36 ET"
    },
    "LAD": {
      "symbol": "LAD",
      "price": 286.52,
      "prevClose": 282.02,
      "updated": "2026-05-05 17:36 ET"
    },
    "ABG": {
      "symbol": "ABG",
      "price": 198.5,
      "prevClose": 193.35,
      "updated": "2026-05-05 17:36 ET"
    },
    "PAG": {
      "symbol": "PAG",
      "price": 168.81,
      "prevClose": 164.91,
      "updated": "2026-05-05 17:36 ET"
    },
    "GES": {
      "symbol": "GES",
      "price": 16.81,
      "prevClose": 16.81,
      "updated": "2026-01-26 15:52 ET"
    },
    "GME": {
      "symbol": "GME",
      "price": 24.23,
      "prevClose": 23.84,
      "updated": "2026-05-05 17:36 ET"
    },
    "AMC": {
      "symbol": "AMC",
      "price": 1.59,
      "prevClose": 1.45,
      "updated": "2026-05-05 17:36 ET"
    },
    "BB": {
      "symbol": "BB",
      "price": 5.6,
      "prevClose": 5.58,
      "updated": "2026-05-05 17:36 ET"
    },
    "BBBY": {
      "symbol": "BBBY",
      "price": 4.98,
      "prevClose": 5.2,
      "updated": "2026-05-05 17:36 ET"
    },
    "KOSS": {
      "symbol": "KOSS",
      "price": 4.41,
      "prevClose": 4.22,
      "updated": "2026-05-05 17:36 ET"
    },
    "SNDL": {
      "symbol": "SNDL",
      "price": 1.43,
      "prevClose": 1.42,
      "updated": "2026-05-05 17:36 ET"
    },
    "CLOV": {
      "symbol": "CLOV",
      "price": 2.61,
      "prevClose": 2.65,
      "updated": "2026-05-05 17:36 ET"
    },
    "WKHS": {
      "symbol": "WKHS",
      "price": 3.18,
      "prevClose": 3.22,
      "updated": "2026-05-05 17:36 ET"
    },
    "SPCE": {
      "symbol": "SPCE",
      "price": 2.45,
      "prevClose": 2.52,
      "updated": "2026-05-05 17:36 ET"
    },
    "SKLZ": {
      "symbol": "SKLZ",
      "price": 6.67,
      "prevClose": 6.8,
      "updated": "2026-05-05 17:36 ET"
    },
    "CLNE": {
      "symbol": "CLNE",
      "price": 2.37,
      "prevClose": 2.42,
      "updated": "2026-05-05 17:36 ET"
    },
    "TLRY": {
      "symbol": "TLRY",
      "price": 5.69,
      "prevClose": 5.9,
      "updated": "2026-05-05 17:36 ET"
    },
    "CGC": {
      "symbol": "CGC",
      "price": 1.08,
      "prevClose": 1.1,
      "updated": "2026-05-05 17:36 ET"
    },
    "ACB": {
      "symbol": "ACB",
      "price": 3.44,
      "prevClose": 3.42,
      "updated": "2026-05-05 17:36 ET"
    },
    "SIRI": {
      "symbol": "SIRI",
      "price": 26.4,
      "prevClose": 26.77,
      "updated": "2026-05-05 17:36 ET"
    },
    "PLUG": {
      "symbol": "PLUG",
      "price": 3.32,
      "prevClose": 3.13,
      "updated": "2026-05-05 17:36 ET"
    },
    "FCEL": {
      "symbol": "FCEL",
      "price": 13.55,
      "prevClose": 13.02,
      "updated": "2026-05-05 17:36 ET"
    },
    "BE": {
      "symbol": "BE",
      "price": 295.25,
      "prevClose": 288.64,
      "updated": "2026-05-05 17:36 ET"
    },
    "QS": {
      "symbol": "QS",
      "price": 7.26,
      "prevClose": 7.19,
      "updated": "2026-05-05 17:36 ET"
    },
    "NKLA": {
      "symbol": "NKLA",
      "price": 0.18,
      "prevClose": 0.18,
      "updated": "2026-02-12 16:00 ET"
    },
    "GOEV": {
      "symbol": "GOEV",
      "price": 0.37,
      "prevClose": 0.37,
      "updated": "2026-04-08 17:11 ET"
    },
    "WOOF": {
      "symbol": "WOOF",
      "price": 2.73,
      "prevClose": 2.78,
      "updated": "2026-05-05 17:36 ET"
    },
    "BARK": {
      "symbol": "BARK",
      "price": 8.97,
      "prevClose": 9.35,
      "updated": "2026-05-05 17:36 ET"
    },
    "CPRI": {
      "symbol": "CPRI",
      "price": 18.6,
      "prevClose": 18.61,
      "updated": "2026-05-05 17:36 ET"
    },
    "BBWI": {
      "symbol": "BBWI",
      "price": 18.4,
      "prevClose": 18.56,
      "updated": "2026-05-05 17:36 ET"
    },
    "PTON": {
      "symbol": "PTON",
      "price": 5.16,
      "prevClose": 5.14,
      "updated": "2026-05-05 17:36 ET"
    },
    "BYND": {
      "symbol": "BYND",
      "price": 0.92,
      "prevClose": 0.94,
      "updated": "2026-05-05 17:36 ET"
    },
    "OUST": {
      "symbol": "OUST",
      "price": 28.6,
      "prevClose": 28.15,
      "updated": "2026-05-05 17:36 ET"
    },
    "LAZR": {
      "symbol": "LAZR",
      "price": 0.06,
      "prevClose": 0.06,
      "updated": "2026-02-24 16:03 ET"
    },
    "LIDR": {
      "symbol": "LIDR",
      "price": 1.97,
      "prevClose": 1.95,
      "updated": "2026-05-05 17:36 ET"
    },
    "JMIA": {
      "symbol": "JMIA",
      "price": 6.72,
      "prevClose": 6.71,
      "updated": "2026-05-05 17:36 ET"
    },
    "VIPS": {
      "symbol": "VIPS",
      "price": 14.12,
      "prevClose": 14.27,
      "updated": "2026-05-05 17:36 ET"
    },
    "BGFV": {
      "symbol": "BGFV",
      "price": 1.44,
      "prevClose": 1.44,
      "updated": "2025-10-03 16:49 ET"
    },
    "PRPL": {
      "symbol": "PRPL",
      "price": 0.49,
      "prevClose": 0.47,
      "updated": "2026-05-05 17:36 ET"
    },
    "CRSR": {
      "symbol": "CRSR",
      "price": 7.12,
      "prevClose": 6.89,
      "updated": "2026-05-05 17:36 ET"
    },
    "APPS": {
      "symbol": "APPS",
      "price": 3.89,
      "prevClose": 3.95,
      "updated": "2026-05-05 17:36 ET"
    },
    "UWMC": {
      "symbol": "UWMC",
      "price": 3.43,
      "prevClose": 3.54,
      "updated": "2026-05-05 17:36 ET"
    },
    "RKT": {
      "symbol": "RKT",
      "price": 14.09,
      "prevClose": 14.01,
      "updated": "2026-05-05 17:36 ET"
    },
    "IONQ": {
      "symbol": "IONQ",
      "price": 48.0,
      "prevClose": 45.75,
      "updated": "2026-05-05 17:36 ET"
    },
    "RGTI": {
      "symbol": "RGTI",
      "price": 18.27,
      "prevClose": 17.7,
      "updated": "2026-05-05 17:36 ET"
    },
    "QUBT": {
      "symbol": "QUBT",
      "price": 9.56,
      "prevClose": 9.5,
      "updated": "2026-05-05 17:36 ET"
    },
    "ARQQ": {
      "symbol": "ARQQ",
      "price": 14.65,
      "prevClose": 14.42,
      "updated": "2026-05-05 17:36 ET"
    },
    "QMCO": {
      "symbol": "QMCO",
      "price": 8.27,
      "prevClose": 7.56,
      "updated": "2026-05-05 17:36 ET"
    },
    "SPY": {
      "symbol": "SPY",
      "price": 723.77,
      "prevClose": 718.01,
      "updated": "2026-05-05 17:36 ET"
    },
    "QQQ": {
      "symbol": "QQQ",
      "price": 681.61,
      "prevClose": 672.88,
      "updated": "2026-05-05 17:36 ET"
    },
    "IWM": {
      "symbol": "IWM",
      "price": 282.56,
      "prevClose": 277.88,
      "updated": "2026-05-05 17:36 ET"
    },
    "DIA": {
      "symbol": "DIA",
      "price": 492.96,
      "prevClose": 489.56,
      "updated": "2026-05-05 17:36 ET"
    },
    "VTI": {
      "symbol": "VTI",
      "price": 356.99,
      "prevClose": 353.98,
      "updated": "2026-05-05 17:36 ET"
    },
    "VOO": {
      "symbol": "VOO",
      "price": 665.3,
      "prevClose": 660.12,
      "updated": "2026-05-05 17:36 ET"
    },
    "ARKK": {
      "symbol": "ARKK",
      "price": 76.58,
      "prevClose": 78.23,
      "updated": "2026-05-05 17:36 ET"
    },
    "ARKG": {
      "symbol": "ARKG",
      "price": 29.78,
      "prevClose": 30.58,
      "updated": "2026-05-05 17:36 ET"
    },
    "ARKW": {
      "symbol": "ARKW",
      "price": 141.65,
      "prevClose": 142.95,
      "updated": "2026-05-05 17:36 ET"
    },
    "ARKF": {
      "symbol": "ARKF",
      "price": 42.07,
      "prevClose": 42.99,
      "updated": "2026-05-05 17:36 ET"
    },
    "GLD": {
      "symbol": "GLD",
      "price": 418.27,
      "prevClose": 414.71,
      "updated": "2026-05-05 17:36 ET"
    },
    "SLV": {
      "symbol": "SLV",
      "price": 65.91,
      "prevClose": 65.94,
      "updated": "2026-05-05 17:36 ET"
    },
    "USO": {
      "symbol": "USO",
      "price": 144.17,
      "prevClose": 147.61,
      "updated": "2026-05-05 17:36 ET"
    },
    "UNG": {
      "symbol": "UNG",
      "price": 10.64,
      "prevClose": 10.95,
      "updated": "2026-05-05 17:36 ET"
    },
    "TLT": {
      "symbol": "TLT",
      "price": 85.43,
      "prevClose": 84.96,
      "updated": "2026-05-05 17:36 ET"
    },
    "HYG": {
      "symbol": "HYG",
      "price": 79.92,
      "prevClose": 79.8,
      "updated": "2026-05-05 17:36 ET"
    },
    "MSTR": {
      "symbol": "MSTR",
      "price": 186.9,
      "prevClose": 183.8,
      "updated": "2026-05-05 17:36 ET"
    },
    "MARA": {
      "symbol": "MARA",
      "price": 12.16,
      "prevClose": 11.83,
      "updated": "2026-05-05 17:36 ET"
    },
    "RIOT": {
      "symbol": "RIOT",
      "price": 20.35,
      "prevClose": 18.68,
      "updated": "2026-05-05 17:36 ET"
    },
    "CLSK": {
      "symbol": "CLSK",
      "price": 13.41,
      "prevClose": 12.82,
      "updated": "2026-05-05 17:36 ET"
    },
    "CIFR": {
      "symbol": "CIFR",
      "price": 22.1,
      "prevClose": 17.89,
      "updated": "2026-05-05 17:36 ET"
    },
    "BITI": {
      "symbol": "BITI",
      "price": 21.38,
      "prevClose": 21.8,
      "updated": "2026-05-05 17:36 ET"
    },
    "SOXL": {
      "symbol": "SOXL",
      "price": 144.16,
      "prevClose": 127.55,
      "updated": "2026-05-05 17:36 ET"
    },
    "TQQQ": {
      "symbol": "TQQQ",
      "price": 67.39,
      "prevClose": 64.91,
      "updated": "2026-05-05 17:36 ET"
    },
    "SQQQ": {
      "symbol": "SQQQ",
      "price": 48.59,
      "prevClose": 50.51,
      "updated": "2026-05-05 17:36 ET"
    },
    "UVXY": {
      "symbol": "UVXY",
      "price": 37.46,
      "prevClose": 37.33,
      "updated": "2026-05-05 17:36 ET"
    },
    "VXX": {
      "symbol": "VXX",
      "price": 28.71,
      "prevClose": 28.67,
      "updated": "2026-05-05 17:36 ET"
    }
  }
}